{
  "Users": [
    {
      "Name": "ขนปุย",
      "Age": "0 Y 2 M",
      "Breed": "Pomeranian",
      "Size": "Small",
      "Color": "Brown",
      "Gender": "Female",
      "About": "รักสงบ น่ารัก ขี้เล่น",
      "Images": [
        "assets/imgs/1.jpg"
      ]
    },
    {
      "Name": "น้องหนู",
      "Age": "0 Y 3 M",
      "Breed": "Chihuahua, Short Coat/Mix",
      "Size": "Small",
      "Color": "Brown/White",
      "Gender": "Female",
      "About": "น้องน่ารักมากเลยค่ะ ขี้อ้อน",
      "Images": [
        "assets/imgs/2.jpg"
      ]
    },
    {
      "Name": "บางรัก",
      "Age": "0 Y 2 M",
      "Breed": "Bangkaew",
      "Size": "Medium",
      "Color": "Brown/White",
      "Gender": "Female",
      "About": "เชื่องมากครับ",
      "Images": [
        "assets/imgs/3.jpg"
      ]
    }
  ]
}
